cs2ics/__init__.py
cs2ics/core.py
cs2ics/exception.py
cs2ics/utils.py
cs2ics-0.2.0.dist-info/LICENSE
cs2ics-0.2.0.dist-info/METADATA
cs2ics-0.2.0.dist-info/WHEEL
cs2ics-0.2.0.dist-info/top_level.txt
cs2ics-0.2.0.dist-info/RECORD
